{"ID":27037,"Author":{"Name":"d33tah","ID":0,"FullName":"","Gravatar":"15098b2b940cacd8b4d07026e01e3102"},"Title":"afl-sid-coverage, fuzzing and automatically generating coverage reports","Description":"\u003cdiv class=\"content\"\u003e\u003cp\u003eMore info here: \u003ca href=\"https://groups.google.com/d/msg/afl-users/efoTrF57Fqc/_ixzf12cEQAJ\"\u003ehttps://groups.google.com/d/msg/afl-users/efoTrF57Fqc/_ixzf12cEQAJ\u003c/a\u003e\u003c/p\u003e\n\u003c/div\u003e","Time":"2015-09-29T17:06:18Z","Tags":["Linux","zsh","xterm-256color"]}